{"nodes": [{"id": "alphabet_q1_2026", "label": "Alphabet Q1 2026 Earnings", "file_type": "document", "source_file": "20260430-Alphabet-Q1-2026\u6c7a\u7b97-Google-AI\u6295\u8cc7\u306e\u679c\u5b9f.html", "source_location": null, "source_url": null, "captured_at": null, "author": null, "contributor": null}], "edges": [{"source": "alphabet_q1_2026", "target": "google_deepmind", "relation": "references", "confidence": "EXTRACTED", "confidence_score": 1.0, "source_file": "20260430-Alphabet-Q1-2026\u6c7a\u7b97-Google-AI\u6295\u8cc7\u306e\u679c\u5b9f.html", "source_location": null, "weight": 1.0}], "hyperedges": []}