{"nodes": [{"id": "minna_bank_ai_automation", "label": "AI Automation at Minna no Bank", "file_type": "document", "source_file": "20260430-\u307f\u3093\u306a\u306e\u9280\u884c-\u821e\u53f0\u88cf-7\u6642\u9593\u30925\u5206\u306b-\u30d7\u30ed\u30b0\u30e9\u30df\u30f3\u30b0\u672a\u7d4c\u9a13-AI\u81ea\u52d5\u5316.html", "source_location": null, "source_url": null, "captured_at": null, "author": null, "contributor": null}, {"id": "minna_bank_gemini_vba", "label": "Gemini VBA Code Generation", "file_type": "document", "source_file": "20260430-\u307f\u3093\u306a\u306e\u9280\u884c-\u821e\u53f0\u88cf-7\u6642\u9593\u30925\u5206\u306b-\u30d7\u30ed\u30b0\u30e9\u30df\u30f3\u30b0\u672a\u7d4c\u9a13-AI\u81ea\u52d5\u5316.html", "source_location": null, "source_url": null, "captured_at": null, "author": null, "contributor": null}, {"id": "minna_bank_rpa_python", "label": "RPA + Python Automation", "file_type": "document", "source_file": "20260430-\u307f\u3093\u306a\u306e\u9280\u884c-\u821e\u53f0\u88cf-7\u6642\u9593\u30925\u5206\u306b-\u30d7\u30ed\u30b0\u30e9\u30df\u30f3\u30b0\u672a\u7d4c\u9a13-AI\u81ea\u52d5\u5316.html", "source_location": null, "source_url": null, "captured_at": null, "author": null, "contributor": null}], "edges": [{"source": "minna_bank_gemini_vba", "target": "minna_bank_ai_automation", "relation": "implements", "confidence": "EXTRACTED", "confidence_score": 1.0, "source_file": "20260430-\u307f\u3093\u306a\u306e\u9280\u884c-\u821e\u53f0\u88cf-7\u6642\u9593\u30925\u5206\u306b-\u30d7\u30ed\u30b0\u30e9\u30df\u30f3\u30b0\u672a\u7d4c\u9a13-AI\u81ea\u52d5\u5316.html", "source_location": null, "weight": 1.0}, {"source": "minna_bank_rpa_python", "target": "minna_bank_ai_automation", "relation": "implements", "confidence": "EXTRACTED", "confidence_score": 1.0, "source_file": "20260430-\u307f\u3093\u306a\u306e\u9280\u884c-\u821e\u53f0\u88cf-7\u6642\u9593\u30925\u5206\u306b-\u30d7\u30ed\u30b0\u30e9\u30df\u30f3\u30b0\u672a\u7d4c\u9a13-AI\u81ea\u52d5\u5316.html", "source_location": null, "weight": 1.0}], "hyperedges": []}